{"summary":"The state\u2019s move continues a trend of state-level regulators moving faster than the feds on regulating crypto.","webName":"coindesk.com","link":"https:\/\/www.coindesk.com\/business\/2022\/09\/23\/washington-state-joins-celsius-bankruptcy-case-as-interested-party\/","publishDate":"2022-09-23T04:00:58","id":16156,"type":null,"title":"Washington State Joins Celsius Bankruptcy Case as Interested Party","category":["Finance"],"content":["The bankruptcy case of beleaguered crypto lending platform Celsius Network has a new interested party: the Washington State Department of Financial Institutions.","Read more: Celsius Network Might Be Planning to Turn Its Debt Into Crypto \u2018IOU\u2019 Tokens"],"entity":[{"type":"Celsius Network","content":"ORGANIZATION"},{"type":"Washington State Department of Financial Institutions","content":"ORGANIZATION"}],"hashtag":["Celsius","Washington","Bankruptcy","Regulation"],"authors":["Sam Reynolds"]}