{"summary":"The town of Newport in Wales could get a hefty reward if the treasure is found in the trash.","webName":"coindesk.com","link":"https:\/\/www.coindesk.com\/markets\/2021\/01\/14\/uk-man-offers-council-72m-if-he-finds-discarded-bitcoin-trove-at-landfill\/","publishDate":"2021-01-14T12:49:52","id":16798,"type":null,"title":"UK Man Offers Council $72M if He Finds Discarded Bitcoin Trove at Landfill","category":["Markets"],"content":["","A U.K. IT engineer who mistakenly threw away a hard drive with around £210 million (US$288 million) of bitcoin on it is asking the local government once again to allow him to search the local landfill for his device.",""],"entity":[{"type":"U.K","content":"LOCATION"},{"type":"US$288 million","content":"MONEY"}],"hashtag":["UK","Hardware","COVID-19"],"authors":["Tanzeel Akhtar"]}