{"summary":"Trezor&#x27;s new CEO Matej Zak says the firm is working on a new flagship hardware product that it will release before the next bull run.","webName":"theblock.co","link":"https:\/\/www.theblock.co\/post\/208854\/trezor-ceo-matej-zak-plans","publishDate":"2023-02-08T03:46:47","id":4189,"type":null,"title":"Trezor\u2019s new CEO looks to freshen wallet lineup while keeping &#x27;conservative&#x27; strategy","category":["COMPANIES"],"content":["<span data-contrast=\"none\" data-v-f87c67ca=\"\"> Matej Zak, the new CEO of crypto wallet maker Trezor, is looking to draw on his product background as he seeks to add \"very usable\" models to its lineup.&nbsp;<\/span>","<span data-contrast=\"none\" data-v-f87c67ca=\"\">Zak joined the Czech company in 2019 as its first product manager, tasked with simplifying the concept of crypto self-custody.<\/span><span data-ccp-props=\"{&quot;134233117&quot;:false,&quot;134233118&quot;:false,&quot;201341983&quot;:0,&quot;335551550&quot;:1,&quot;335551620&quot;:1,&quot;335559685&quot;:0,&quot;335559737&quot;:0,&quot;335559738&quot;:0,&quot;335559739&quot;:160,&quot;335559740&quot;:259}\" data-v-f87c67ca=\"\"> Now he's stepped up to the top job, and he's preaching evolution not revolution.&nbsp;<\/span>","<span data-contrast=\"none\" data-v-f87c67ca=\"\">\u201CI\u2019m not a technical person,\" said Zak, who trained as a musician from the age of seven and studied at Berklee College of Music in Boston. \"Y<\/span><span data-contrast=\"none\" data-v-f87c67ca=\"\">et that\u2019s why I really love this challenge because it\u2019s basically making something really complicated into very usable and very user friendly.\u201D<\/span><span data-ccp-props=\"{&quot;134233117&quot;:false,&quot;134233118&quot;:false,&quot;201341983&quot;:0,&quot;335551550&quot;:1,&quot;335551620&quot;:1,&quot;335559685&quot;:0,&quot;335559737&quot;:0,&quot;335559738&quot;:0,&quot;335559739&quot;:160,&quot;335559740&quot;:259}\" data-v-f87c67ca=\"\">&nbsp;<\/span>","<span data-contrast=\"none\" data-v-f87c67ca=\"\">As Trezor\u2019s first product hire, Zak would frequently sit in meetings alongside co-founders Marek Palatinus and Pavol Rusnak as the company grew to 120 people. Before taking the CEO role, he also spent about a year shadowing Palatinus, his predecessor.<\/span><span data-ccp-props=\"{&quot;134233117&quot;:false,&quot;134233118&quot;:false,&quot;201341983&quot;:0,&quot;335551550&quot;:1,&quot;335551620&quot;:1,&quot;335559685&quot;:0,&quot;335559737&quot;:0,&quot;335559738&quot;:0,&quot;335559739&quot;:160,&quot;335559740&quot;:259}\" data-v-f87c67ca=\"\">&nbsp;<\/span>","<span data-contrast=\"none\" data-v-f87c67ca=\"\">\u201CWe are not a small company, it's a huge challenge,\u201D Zak said. \u201CI won't lie about that, it's a big responsibility. We are talking about millions of users in the Trezor ecosystem and many more to come.\u201D<\/span><span data-ccp-props=\"{&quot;134233117&quot;:false,&quot;134233118&quot;:false,&quot;201341983&quot;:0,&quot;335551550&quot;:1,&quot;335551620&quot;:1,&quot;335559685&quot;:0,&quot;335559737&quot;:0,&quot;335559738&quot;:0,&quot;335559739&quot;:160,&quot;335559740&quot;:259}\" data-v-f87c67ca=\"\">&nbsp;<\/span>","<span data-contrast=\"none\" data-v-f87c67ca=\"\">Trezor is one of the oldest brands in crypto, having been founded in 2013. The company tries to lean on this legacy to keep its edge in the market, Zak said. <\/span><span data-ccp-props=\"{&quot;134233117&quot;:false,&quot;134233118&quot;:false,&quot;201341983&quot;:0,&quot;335551550&quot;:1,&quot;335551620&quot;:1,&quot;335559685&quot;:0,&quot;335559737&quot;:0,&quot;335559738&quot;:0,&quot;335559739&quot;:160,&quot;335559740&quot;:259}\" data-v-f87c67ca=\"\">&nbsp;<\/span>","<span data-contrast=\"none\" data-v-f87c67ca=\"\">It\u2019s also a notable crypto startup without outside investors \u2014 a rarity in an industry that has <\/span><a href=\"https:\/\/www.theblock.co\/linked\/128397\/crypto-companies-raised-just-over-25-billion-in-venture-funding-during-2021\" data-v-f87c67ca=\"\"><span data-contrast=\"none\" data-v-f87c67ca=\"\">received<\/span><\/a><span data-contrast=\"none\" data-v-f87c67ca=\"\"> an abundance of funding in recent years.<\/span><span data-ccp-props=\"{&quot;134233117&quot;:false,&quot;134233118&quot;:false,&quot;201341983&quot;:0,&quot;335551550&quot;:1,&quot;335551620&quot;:1,&quot;335559685&quot;:0,&quot;335559737&quot;:0,&quot;335559738&quot;:0,&quot;335559739&quot;:160,&quot;335559740&quot;:259}\" data-v-f87c67ca=\"\">&nbsp;<\/span>","<span data-contrast=\"none\" data-v-f87c67ca=\"\">It's \u201Csomething we are proud of to be honest and something which, in general, is a direction we want to go in because the idea is we don't want any venture money to tell us what's right for the user,\u201D Zak said.<\/span><span data-ccp-props=\"{&quot;134233117&quot;:false,&quot;134233118&quot;:false,&quot;201341983&quot;:0,&quot;335551550&quot;:1,&quot;335551620&quot;:1,&quot;335559685&quot;:0,&quot;335559737&quot;:0,&quot;335559738&quot;:0,&quot;335559739&quot;:160,&quot;335559740&quot;:259}\" data-v-f87c67ca=\"\">&nbsp;<\/span>","<span data-contrast=\"none\" data-v-f87c67ca=\"\">In some ways Trezor\u2019s legacy is now its biggest challenge, however. Its two hardware products, the Model One and the Model T, were launched in 2014 and 2018, respectively. One of Zak\u2019s top priorities is refreshing these products as the company works on \"<\/span><span data-contrast=\"none\" data-v-f87c67ca=\"\">a brand-new flagship product that we want to bring before the next bull run,\u201D he said.<\/span><span data-ccp-props=\"{&quot;134233117&quot;:false,&quot;134233118&quot;:false,&quot;201341983&quot;:0,&quot;335551550&quot;:1,&quot;335551620&quot;:1,&quot;335559685&quot;:0,&quot;335559737&quot;:0,&quot;335559738&quot;:0,&quot;335559739&quot;:160,&quot;335559740&quot;:259}\" data-v-f87c67ca=\"\">&nbsp;<\/span>","<span data-contrast=\"none\" data-v-f87c67ca=\"\">Even with crypto prices in a funk, the hardware wallet market has become increasingly competitive. Trezor's big rival Ledger is <\/span><a href=\"https:\/\/www.theblock.co\/post\/192849\/ledger-pascal-gauthier-web3-apple\" data-v-f87c67ca=\"\"><span data-contrast=\"none\" data-v-f87c67ca=\"\">looking<\/span><\/a><span data-contrast=\"none\" data-v-f87c67ca=\"\"> to become the \u201CApple of web3.\u201D And startups like <\/span><a href=\"https:\/\/www.theblock.co\/post\/196174\/polychain-capital-leads-bitcoin-wallet-developer-foundations-7-million-raise\" data-v-f87c67ca=\"\"><span data-contrast=\"none\" data-v-f87c67ca=\"\">Foundation<\/span><\/a><span data-contrast=\"none\" data-v-f87c67ca=\"\"> and <\/span><a href=\"https:\/\/www.theblock.co\/post\/191744\/ngrave-looks-to-raise-15-million-series-a-at-60-million-pre-money-valuation\" data-v-f87c67ca=\"\"><span data-contrast=\"none\" data-v-f87c67ca=\"\">Ngrave<\/span><\/a> are snapping at their heels.&nbsp;","<span data-contrast=\"none\" data-v-f87c67ca=\"\">Still, self-custody has become a hot topic in the bear market following the collapse of centralized crypto players such as lender Celsius and exchange giant FTX. Many who lost crypto held on these platforms could have avoided that fate if they'd used their own hardware wallet. Both Trezor and Ledger\u2019s sales <\/span><a href=\"https:\/\/www.theblock.co\/post\/188754\/binance-labs-makes-strategic-investment-in-hardware-wallet-maker-ngrave\" data-v-f87c67ca=\"\"><span data-contrast=\"none\" data-v-f87c67ca=\"\">spiked<\/span><\/a><span data-contrast=\"none\" data-v-f87c67ca=\"\"> following November's downfall of FTX.<\/span><span data-ccp-props=\"{&quot;134233117&quot;:false,&quot;134233118&quot;:false,&quot;201341983&quot;:0,&quot;335551550&quot;:1,&quot;335551620&quot;:1,&quot;335559685&quot;:0,&quot;335559737&quot;:0,&quot;335559738&quot;:0,&quot;335559739&quot;:160,&quot;335559740&quot;:259}\" data-v-f87c67ca=\"\">&nbsp;<\/span>","<span data-contrast=\"none\" data-v-f87c67ca=\"\">Trezor doesn\u2019t want to rest on its laurels, despite that unexpected boost. This year it plans to take more of the mainstream consumer electronics market.&nbsp;<\/span>","<span data-contrast=\"none\" data-v-f87c67ca=\"\">The team is building a software suite for mobile devices, which aims to give users a whole portfolio of options when it comes to using their Trezor \u2014 whether that\u2019s checking their funds or buying and selling crypto.<\/span><span data-ccp-props=\"{&quot;134233117&quot;:false,&quot;134233118&quot;:false,&quot;201341983&quot;:0,&quot;335551550&quot;:1,&quot;335551620&quot;:1,&quot;335559685&quot;:0,&quot;335559737&quot;:0,&quot;335559738&quot;:0,&quot;335559739&quot;:160,&quot;335559740&quot;:259}\" data-v-f87c67ca=\"\"> The new flagship product will have bluetooth, making it easier to connect to its software suite without a USB cable, Zak said.<\/span>","<span data-contrast=\"none\" data-v-f87c67ca=\"\">\u201CIt's all about the portability of these things,\u201D he explained.<\/span>","<span data-contrast=\"none\" data-v-f87c67ca=\"\">Even as Trezor powers ahead with its vision for hardware products and sees growth in the bear market at a time when many other players are faltering, it's still operating with the \u201Cconservative\u201D approach that\u2019s helped it thrive since 2013.<\/span><span data-ccp-props=\"{&quot;134233117&quot;:false,&quot;134233118&quot;:false,&quot;201341983&quot;:0,&quot;335551550&quot;:1,&quot;335551620&quot;:1,&quot;335559685&quot;:0,&quot;335559737&quot;:0,&quot;335559738&quot;:0,&quot;335559739&quot;:160,&quot;335559740&quot;:259}\" data-v-f87c67ca=\"\">&nbsp;<\/span>","<span data-contrast=\"none\" data-v-f87c67ca=\"\">While Trezor currently has a hiring freeze in place, Zak said it will need to invest in some new hires for the hardware business this year.<\/span><span data-ccp-props=\"{&quot;134233117&quot;:false,&quot;134233118&quot;:false,&quot;201341983&quot;:0,&quot;335551550&quot;:1,&quot;335551620&quot;:1,&quot;335559685&quot;:0,&quot;335559737&quot;:0,&quot;335559738&quot;:0,&quot;335559739&quot;:160,&quot;335559740&quot;:259}\" data-v-f87c67ca=\"\">&nbsp;<\/span>","<span data-contrast=\"none\" data-v-f87c67ca=\"\">\u201CWe are more on the conservative side,\u201D Zak said. \u201CWe wait and see what\u2019s happening. If there is really real-life use cases and only then we act on implementing it within the ecosystem.\u201D<\/span><span data-ccp-props=\"{&quot;134233117&quot;:false,&quot;134233118&quot;:false,&quot;201341983&quot;:0,&quot;335551550&quot;:1,&quot;335551620&quot;:1,&quot;335559685&quot;:0,&quot;335559737&quot;:0,&quot;335559738&quot;:0,&quot;335559739&quot;:160,&quot;335559740&quot;:259}\" data-v-f87c67ca=\"\">&nbsp;<\/span>","<span data-contrast=\"none\" data-v-f87c67ca=\"\">The outlook for when the company might ramp up its business really depends on when the next bull run comes, Zak said. It\u2019s currently predicting the crypto market will be strongest sometime in 2025, based on bitcoin halvings as well as past sales and prices. But ultimately, it\u2019s sheer speculation, he added.<\/span><span data-ccp-props=\"{&quot;134233117&quot;:false,&quot;134233118&quot;:false,&quot;201341983&quot;:0,&quot;335551550&quot;:1,&quot;335551620&quot;:1,&quot;335559685&quot;:0,&quot;335559737&quot;:0,&quot;335559738&quot;:0,&quot;335559739&quot;:160,&quot;335559740&quot;:259}\" data-v-f87c67ca=\"\">&nbsp;<\/span>","<span data-contrast=\"none\" data-v-f87c67ca=\"\">\u201CWe are also prepared for scenarios where the bull market picks up tomorrow and so that's something very specific about this about the market in general,\u201D Zak said. \u201CYou really never know, and we have to work with certain level of uncertainty and volatility and that's the job, right?\u201D<\/span><span data-ccp-props=\"{&quot;134233117&quot;:false,&quot;134233118&quot;:false,&quot;201341983&quot;:0,&quot;335551550&quot;:1,&quot;335551620&quot;:1,&quot;335559685&quot;:0,&quot;335559737&quot;:0,&quot;335559738&quot;:0,&quot;335559739&quot;:160,&quot;335559740&quot;:259}\" data-v-f87c67ca=\"\">&nbsp;<\/span>","© 2023 The Block. All Rights Reserved. This article is provided for informational purposes only. It is not offered or intended to be used as legal, tax, investment, financial, or other advice."],"entity":[{"type":"2014","content":"DATE"},{"type":"2025","content":"DATE"},{"type":"Matej Zak","content":"PERSON"},{"type":"Foundation","content":"ORGANIZATION"},{"type":"Marek Palatinus","content":"PERSON"},{"type":"2023","content":"DATE"},{"type":"2013","content":"DATE"},{"type":"Berklee College of Music","content":"ORGANIZATION"},{"type":"Zak","content":"PERSON"},{"type":"2018","content":"DATE"},{"type":"2019","content":"DATE"},{"type":"FTX","content":"ORGANIZATION"},{"type":"November","content":"DATE"},{"type":"Pavol Rusnak","content":"PERSON"},{"type":"Trezor\u2019s","content":"ORGANIZATION"},{"type":"Boston","content":"LOCATION"}],"hashtag":["WALLET MAKERS","WALLETS"],"authors":["Kari McMahon","The Block"]}